cli.py
weaviate_cli/__init__.py
weaviate_cli/defaults.py
weaviate_cli/utils.py
weaviate_cli/commands/__init__.py
weaviate_cli/commands/assign.py
weaviate_cli/commands/cancel.py
weaviate_cli/commands/create.py
weaviate_cli/commands/delete.py
weaviate_cli/commands/get.py
weaviate_cli/commands/query.py
weaviate_cli/commands/restore.py
weaviate_cli/commands/revoke.py
weaviate_cli/commands/update.py
weaviate_cli/completion/__init__.py
weaviate_cli/completion/complete.py
weaviate_cli/datasets/__init__.py
weaviate_cli/datasets/movies.json
weaviate_cli/managers/__init__.py
weaviate_cli/managers/alias_manager.py
weaviate_cli/managers/backup_manager.py
weaviate_cli/managers/cluster_manager.py
weaviate_cli/managers/collection_manager.py
weaviate_cli/managers/config_manager.py
weaviate_cli/managers/data_manager.py
weaviate_cli/managers/node_manager.py
weaviate_cli/managers/role_manager.py
weaviate_cli/managers/shard_manager.py
weaviate_cli/managers/tenant_manager.py
weaviate_cli/managers/user_manager.py
weaviate_cli/types/models.py
weaviate_cli-3.2.4.dist-info/licenses/LICENSE
weaviate_cli-3.2.4.dist-info/METADATA
weaviate_cli-3.2.4.dist-info/WHEEL
weaviate_cli-3.2.4.dist-info/entry_points.txt
weaviate_cli-3.2.4.dist-info/top_level.txt
weaviate_cli-3.2.4.dist-info/RECORD
