Metadata-Version: 2.4
Name: weaviate-cli
Version: 3.2.4
Summary: Command line interface to interact with weaviate
Home-page: https://github.com/weaviate/weaviate-cli
Download-URL: https://github.com/weaviate/weaviate-cli
Author: Weaviate
Author-email: hello@weaviate.io
License: BSD 3-clause
Project-URL: Docs, https://github.com/weaviate/weaviate-cli/blob/main/README.rst
Project-URL: Bugs, https://github.com/weaviate/weaviate-cli/issues
Keywords: cli,weaviate
Platform: Linux
Classifier: Development Status :: 3 - Alpha
Classifier: Environment :: Console
Classifier: Intended Audience :: Developers
Classifier: Natural Language :: English
Classifier: License :: OSI Approved :: GNU General Public License (GPL)
Classifier: Operating System :: POSIX :: Linux
Classifier: Programming Language :: Python
Classifier: Programming Language :: Python :: 3
Classifier: Programming Language :: Python :: 3 :: Only
Classifier: Programming Language :: Python :: 3.9
Classifier: Programming Language :: Python :: 3.10
Classifier: Programming Language :: Python :: 3.11
Classifier: Programming Language :: Python :: 3.12
Classifier: Programming Language :: Python :: Implementation :: CPython
Requires-Python: >=3.9
License-File: LICENSE
Requires-Dist: weaviate-client>=4.16.7
Requires-Dist: click==8.1.7
Requires-Dist: semver>=3.0.2
Requires-Dist: numpy>=1.24.0
Requires-Dist: importlib-resources>=5.0.0
Requires-Dist: prettytable>=3.1.0
Requires-Dist: faker>=20.0.0
Dynamic: download-url
Dynamic: license-file
